pyamlo/__about__.py
pyamlo/__init__.py
pyamlo/config.py
pyamlo/merge.py
pyamlo/resolve.py
pyamlo/tags.py
pyamlo-0.1.dev27.dist-info/METADATA
pyamlo-0.1.dev27.dist-info/WHEEL
pyamlo-0.1.dev27.dist-info/entry_points.txt
pyamlo-0.1.dev27.dist-info/licenses/LICENSE
pyamlo-0.1.dev27.dist-info/RECORD
