Metadata-Version: 2.4
Name: pyamlo
Version: 0.1.dev27
Summary: YAML configuration loader with advanced features.
Author-email: Mart van Rijthoven <your@email.com>
License: MIT License
License-File: LICENSE
Keywords: configuration,interpolation,loader,yaml
Classifier: Development Status :: 4 - Beta
Classifier: Intended Audience :: Developers
Classifier: License :: OSI Approved :: MIT License
Classifier: Programming Language :: Python :: 3
Classifier: Programming Language :: Python :: 3.12
Classifier: Topic :: Software Development :: Libraries :: Python Modules
Requires-Python: >=3.12
Requires-Dist: pyyaml>=6.0
Provides-Extra: dev
Requires-Dist: black>=23.0.0; extra == 'dev'
Requires-Dist: mypy>=1.0.0; extra == 'dev'
Requires-Dist: pyyamlo[docs,test]; extra == 'dev'
Requires-Dist: ruff>=0.1.0; extra == 'dev'
Requires-Dist: types-pyyaml; extra == 'dev'
Provides-Extra: docs
Requires-Dist: mkdocs-git-committers-plugin; extra == 'docs'
Requires-Dist: mkdocs-git-revision-date-localized-plugin>=1.2.0; extra == 'docs'
Requires-Dist: mkdocs-material>=9.0.0; extra == 'docs'
Requires-Dist: mkdocs>=1.5.0; extra == 'docs'
Requires-Dist: mkdocstrings[python]>=0.20.0; extra == 'docs'
Provides-Extra: test
Requires-Dist: pytest; extra == 'test'
Requires-Dist: pytest-cov; extra == 'test'
